.hgignore
CHANGES.txt
LICENSE.txt
README.txt
bootstrap.py
buildout.cfg
setup.py
js/__init__.py
js.jquery_joyride.egg-info/PKG-INFO
js.jquery_joyride.egg-info/SOURCES.txt
js.jquery_joyride.egg-info/dependency_links.txt
js.jquery_joyride.egg-info/entry_points.txt
js.jquery_joyride.egg-info/namespace_packages.txt
js.jquery_joyride.egg-info/not-zip-safe
js.jquery_joyride.egg-info/requires.txt
js.jquery_joyride.egg-info/top_level.txt
js/jquery_joyride/__init__.py
js/jquery_joyride/test_joyride.txt
js/jquery_joyride/resources/README.txt
js/jquery_joyride/resources/joyride-dadb4d120f.css
js/jquery_joyride/resources/jquery.joyride-dadb4d120f.js
js/jquery_joyride/resources/jquery.joyride.min-dadb4d120f.js