Metadata-Version: 1.0
Name: js.jquery-joyride
Version: 1.0.3a1dev
Summary: Fanstatic packaging of joyride
Home-page: UNKNOWN
Author: Fanstatic Developers
Author-email: fanstatic@googlegroups.com
License: BSD
Platform: UNKNOWN
